auraparse_mcp/__init__.py
auraparse_mcp/server.py
auraparse_mcp-0.1.0.dist-info/METADATA
auraparse_mcp-0.1.0.dist-info/WHEEL
auraparse_mcp-0.1.0.dist-info/entry_points.txt
auraparse_mcp-0.1.0.dist-info/RECORD
