Metadata-Version: 2.4
Name: auraparse-mcp
Version: 0.1.0
Summary: Official MCP Server for AuraParse - The AI Financial Document Intelligence API
Project-URL: Homepage, https://auraparse.web.app
Author-email: Simpaira Ltd <info@simpaira.com>
Requires-Python: >=3.10
Requires-Dist: httpx
Requires-Dist: mcp
